GeoConformalizedExplainer/GeoConformal.py
GeoConformalizedExplainer/GeoConformalizedExplainer.py
GeoConformalizedExplainer/__init__.py
GeoConformalizedExplainer/_version.py
GeoConformalizedExplainer/model.py
geoxcp-1.0.0.dist-info/licenses/LICENSE
geoxcp-1.0.0.dist-info/METADATA
geoxcp-1.0.0.dist-info/WHEEL
geoxcp-1.0.0.dist-info/top_level.txt
geoxcp-1.0.0.dist-info/RECORD
