Metadata-Version: 2.4
Name: GeoXCP
Version: 1.0.0
Summary: Geospatial eXplanation Conformal Prediction (GeoXCP)
Author-email: Xiayin Lou <xiayin.lou@tum.de>
License-Expression: MIT
Requires-Python: >=3.8
License-File: LICENSE
Dynamic: license-file
